swh/graphql/__init__.py
swh/graphql/app.py
swh/graphql/gunicorn_config.py
swh/graphql/server.py
swh/graphql/backends/__init__.py
swh/graphql/backends/archive.py
swh/graphql/backends/search.py
swh/graphql/client/__init__.py
swh/graphql/client/explorer.html
swh/graphql/client/view.py
swh/graphql/client/static/favicon.png
swh/graphql/config/dev.yml
swh/graphql/config/staging.yml
swh/graphql/config/test.yml
swh/graphql/errors/__init__.py
swh/graphql/errors/errors.py
swh/graphql/errors/handlers.py
swh/graphql/middlewares/__init__.py
swh/graphql/middlewares/logger.py
swh/graphql/resolvers/__init__.py
swh/graphql/resolvers/base_connection.py
swh/graphql/resolvers/base_node.py
swh/graphql/resolvers/content.py
swh/graphql/resolvers/content_data.py
swh/graphql/resolvers/directory.py
swh/graphql/resolvers/directory_entry.py
swh/graphql/resolvers/origin.py
swh/graphql/resolvers/person.py
swh/graphql/resolvers/release.py
swh/graphql/resolvers/resolver_factory.py
swh/graphql/resolvers/resolvers.py
swh/graphql/resolvers/revision.py
swh/graphql/resolvers/scalars.py
swh/graphql/resolvers/search.py
swh/graphql/resolvers/snapshot.py
swh/graphql/resolvers/snapshot_branch.py
swh/graphql/resolvers/swhid.py
swh/graphql/resolvers/target.py
swh/graphql/resolvers/visit.py
swh/graphql/resolvers/visit_status.py
swh/graphql/schema/schema.graphql
swh/graphql/tests/__init__.py
swh/graphql/tests/data.py
swh/graphql/tests/test_view.py
swh/graphql/tests/functional/__init__.py
swh/graphql/tests/functional/test_content.py
swh/graphql/tests/functional/test_content_data_node.py
swh/graphql/tests/functional/test_directory.py
swh/graphql/tests/functional/test_directory_entry.py
swh/graphql/tests/functional/test_errors.py
swh/graphql/tests/functional/test_logger.py
swh/graphql/tests/functional/test_origin_connection.py
swh/graphql/tests/functional/test_origin_node.py
swh/graphql/tests/functional/test_pagination.py
swh/graphql/tests/functional/test_query_cost.py
swh_graphql-0.1.0.dist-info/licenses/AUTHORS
swh_graphql-0.1.0.dist-info/licenses/LICENSE
swh_graphql-0.1.0.dist-info/METADATA
swh_graphql-0.1.0.dist-info/WHEEL
swh_graphql-0.1.0.dist-info/top_level.txt
swh_graphql-0.1.0.dist-info/RECORD
