Metadata-Version: 2.4
Name: swh.graphql
Version: 0.1.0
Summary: Software Heritage GraphQL APIs
Author-email: Software Heritage developers <swh-devel@inria.fr>
Project-URL: Homepage, https://gitlab.softwareheritage.org/swh/devel/swh-graphql
Project-URL: Bug Reports, https://gitlab.softwareheritage.org/swh/devel/swh-graphql/-/issues
Project-URL: Funding, https://www.softwareheritage.org/donate
Project-URL: Documentation, https://docs.softwareheritage.org/devel/swh-graphql/
Project-URL: Source, https://gitlab.softwareheritage.org/swh/devel/swh-graphql.git
Classifier: Programming Language :: Python :: 3
Classifier: Intended Audience :: Developers
Classifier: License :: OSI Approved :: GNU General Public License v3 (GPLv3)
Classifier: Operating System :: OS Independent
Classifier: Development Status :: 3 - Alpha
Requires-Python: >=3.7
License-File: LICENSE
License-File: AUTHORS
Requires-Dist: ariadne>=0.20.1
Requires-Dist: uvicorn
Requires-Dist: starlette
Requires-Dist: httpx
Requires-Dist: aiocache[memcached]
Requires-Dist: sentry-sdk>=1.32.0
Requires-Dist: swh.core[http]>=3.7.0
Requires-Dist: swh.storage>=1.15.3
Requires-Dist: swh.model>=6.14.0
Requires-Dist: swh.search
Requires-Dist: swh.auth>=0.7.2
Provides-Extra: testing
Requires-Dist: pytest>=8.1; extra == "testing"
Requires-Dist: pytest-mock; extra == "testing"
Requires-Dist: swh.core[testing]>=3.7.0; extra == "testing"
Requires-Dist: types-PyYAML; extra == "testing"
Dynamic: license-file
